message_handler/__init__.py
message_handler/message_handler.py
ops_py_message_handler-1.0.7.dist-info/LICENSE
ops_py_message_handler-1.0.7.dist-info/METADATA
ops_py_message_handler-1.0.7.dist-info/WHEEL
ops_py_message_handler-1.0.7.dist-info/top_level.txt
ops_py_message_handler-1.0.7.dist-info/RECORD
